django_generic_plus-3.1.0.dist-info/licenses/LICENSE
generic_plus/__init__.py
generic_plus/compat.py
generic_plus/fields.py
generic_plus/models.py
generic_plus/utils.py
generic_plus/curation/__init__.py
generic_plus/curation/fields.py
generic_plus/curation/forms.py
generic_plus/curation/widgets.py
generic_plus/forms/__init__.py
generic_plus/forms/widgets.py
generic_plus/templates/generic_plus/blank.html
generic_plus/templates/generic_plus/custom_field.html
generic_plus/templates/generic_plus/inline.html
generic_plus/tests/__init__.py
generic_plus/tests/conftest.py
generic_plus/tests/settings.py
generic_plus/tests/test_curation/__init__.py
generic_plus/tests/test_curation/admin.py
generic_plus/tests/test_curation/models.py
generic_plus/tests/test_curation/test_generic_curation.py
generic_plus/tests/test_curation/urls.py
generic_plus/tests/test_filefield/__init__.py
generic_plus/tests/test_filefield/admin.py
generic_plus/tests/test_filefield/fields.py
generic_plus/tests/test_filefield/models.py
generic_plus/tests/test_filefield/test_models.py
generic_plus/tests/test_filefield/urls.py
django_generic_plus-3.1.0.dist-info/METADATA
django_generic_plus-3.1.0.dist-info/WHEEL
django_generic_plus-3.1.0.dist-info/top_level.txt
django_generic_plus-3.1.0.dist-info/RECORD
